misleep/__init__.py
misleep-1.0.1.dist-info/LICENSE
misleep-1.0.1.dist-info/METADATA
misleep-1.0.1.dist-info/WHEEL
misleep-1.0.1.dist-info/top_level.txt
misleep-1.0.1.dist-info/RECORD
