Metadata-Version: 2.1
Name: misleep
Version: 1.0.1
Summary: MiSleep: Mice Sleep EEG/EMG visualization, scoring and analysis.
Home-page: https://github.com/BryanWang0702/MiSleep/
Download-URL: https://github.com/BryanWang0702/MiSleep/
Author: Xueqiang Wang
Author-email: swang@gmail.com
Maintainer: Xueqiang Wang
Maintainer-email: swang@gmail.com
License: BSD (3-clause)
Classifier: Intended Audience :: Science/Research
Classifier: Programming Language :: Python :: 3.8
Classifier: Programming Language :: Python :: 3.9
Classifier: Programming Language :: Python :: 3.10
Classifier: Programming Language :: Python :: 3.11
Classifier: License :: OSI Approved :: BSD License
Classifier: Operating System :: POSIX
Classifier: Operating System :: Unix
Classifier: Operating System :: MacOS
License-File: LICENSE
Requires-Dist: numpy >=1.18.1
Requires-Dist: matplotlib
Requires-Dist: scipy
Requires-Dist: pyedflib
Requires-Dist: hdf5storage
